clusterir/__init__.py
clusterir-0.1.1.dist-info/METADATA
clusterir-0.1.1.dist-info/WHEEL
clusterir-0.1.1.dist-info/top_level.txt
clusterir-0.1.1.dist-info/RECORD
