Metadata-Version: 2.4
Name: clusterir
Version: 0.1.1
Summary: Clustering for Information Retrieval
Author: Aryan Bhagwat
Author-email: legendasur531@gmail.com
Classifier: Programming Language :: Python :: 3
Classifier: Operating System :: OS Independent
Requires-Python: >=3.6
Dynamic: author
Dynamic: author-email
Dynamic: classifier
Dynamic: requires-python
Dynamic: summary
